jito_py/__init__.py
jito_py/block_engine.py
jito_py/searcher.py
jito_py-0.1.3.dist-info/LICENSE
jito_py-0.1.3.dist-info/METADATA
jito_py-0.1.3.dist-info/WHEEL
jito_py-0.1.3.dist-info/top_level.txt
jito_py-0.1.3.dist-info/RECORD
