Metadata-Version: 2.1
Name: jito-py
Version: 0.1.3
Summary: A Python library for interacting with the Jito JSON-RPC
Author-email: "Matrix.Ye" <initsysctrl@outlook.com>
License: MIT
Project-URL: Homepage, https://github.com/MatrixYe/jito-py
Keywords: jito,solana,json-rpc
Classifier: Programming Language :: Python :: 3
Classifier: License :: OSI Approved :: MIT License
Classifier: Operating System :: OS Independent
Requires-Python: >=3.6
License-File: LICENSE
Requires-Dist: requests
